{
  "project_info": {
    "project_number": "618236770067",
    "project_id": "my-people-e916f",
    "storage_bucket": "my-people-e916f.firebasestorage.app"
  },
  "client": [
    {
      "client_info": {
        "mobilesdk_app_id": "1:618236770067:android:e186803587272f5bc94ce6",
        "android_client_info": {
          "package_name": "com.infiniteants.mypeople"
        }
      },
      "oauth_client": [],
      "api_key": [
        {
          "current_key": "AIzaSyCJHpUcX257g6JHX5KOP3GX8CBTdZ_33gY"
        }
      ],
      "services": {
        "appinvite_service": {
          "other_platform_oauth_client": []
        }
      }
    }
  ],
  "configuration_version": "1"
}